br_common/__init__.py
br_common/enums/__init__.py
br_common/enums/enums.py
br_common/features/__init__.py
br_common/features/auth/__init__.py
br_common/features/auth/models.py
br_common/features/customer/__init__.py
br_common/features/customer/models.py
br_common/features/employee/__init__.py
br_common/features/employee/models.py
br_common/features/sales/__init__.py
br_common/features/sales/models.py
br_common/features/trips/__init__.py
br_common/features/trips/models.py
br_common/models/__init__.py
br_common/models/models.py
br_common/services/__init__.py
br_common/services/aws_service.py
br_common/services/unifonic_service.py
br_common/tasks/__init__.py
br_common/tasks/dev/__init__.py
br_common/tasks/dev/dev.py
br_common/tasks/run/__init__.py
br_common/tasks/run/run.py
br_common/utils/__init__.py
br_common/utils/utils.py
br_common-0.0.16.dist-info/METADATA
br_common-0.0.16.dist-info/WHEEL
br_common-0.0.16.dist-info/top_level.txt
br_common-0.0.16.dist-info/RECORD
