Metadata-Version: 2.1
Name: br_common
Version: 0.0.16
Summary: A python project common code package
Author: Gaurav Mahale
Author-email: gaurav.mahale@aventior.com
Classifier: Programming Language :: Python :: 3
Classifier: License :: OSI Approved :: MIT License
Classifier: Operating System :: OS Independent
